README.md
setup.py
chimera_utils/__init__.py
chimera_utils/annotation.py
chimera_utils/count.py
chimera_utils/logger.py
chimera_utils/parser.py
chimera_utils/process.py
chimera_utils/run.py
chimera_utils/version.py
chimera_utils.egg-info/PKG-INFO
chimera_utils.egg-info/SOURCES.txt
chimera_utils.egg-info/dependency_links.txt
chimera_utils.egg-info/entry_points.txt
chimera_utils.egg-info/requires.txt
chimera_utils.egg-info/top_level.txt