Metadata-Version: 1.1
Name: chimera-utils
Version: 0.5.1
Summary: Python tools for processing chimeric reads and lists of gene fusions.
Home-page: https://github.com/friend1ws/chimera_utils
Author: Yuichi Shiraishi
Author-email: friend1ws@gamil.com
License: GPLv3
Platform: UNKNOWN
Classifier: Development Status :: 4 - Beta
Classifier: Intended Audience :: Science/Research
Classifier: License :: OSI Approved :: GNU General Public License v3 (GPLv3)
Classifier: Operating System :: Unix
Classifier: Programming Language :: Python :: 2.7
Classifier: Topic :: Scientific/Engineering :: Bio-Informatics
